interior_preview_bot/__init__.py
interior_preview_bot/core.py
interior_preview_bot-0.1.0.dist-info/licenses/LICENSE
interior_preview_bot-0.1.0.dist-info/METADATA
interior_preview_bot-0.1.0.dist-info/WHEEL
interior_preview_bot-0.1.0.dist-info/top_level.txt
interior_preview_bot-0.1.0.dist-info/RECORD
