Metadata-Version: 2.4
Name: interior_preview_bot
Version: 0.1.0
Summary: A Python package to generate interior design previews using Poe API models.
Author: Gemini
Author-email: NewJerseyStyle <work.source.wishes@gmail.com>
Project-URL: Homepage, https://github.com/NewJerseyStyle/interior_preview_bot
Project-URL: Bug Tracker, https://github.com/NewJerseyStyle/interior_preview_bot/issues
Classifier: Programming Language :: Python :: 3
Classifier: License :: OSI Approved :: MIT License
Classifier: Operating System :: OS Independent
Requires-Python: >=3.7
License-File: LICENSE
Requires-Dist: openai
Dynamic: license-file
